apiapp.py
colors.py
newapp.py
torn.py
torn-0.0.3.dist-info/DESCRIPTION.rst
torn-0.0.3.dist-info/METADATA
torn-0.0.3.dist-info/RECORD
torn-0.0.3.dist-info/WHEEL
torn-0.0.3.dist-info/entry_points.txt
torn-0.0.3.dist-info/metadata.json
torn-0.0.3.dist-info/top_level.txt
