Metadata-Version: 2.0
Name: torn
Version: 0.0.3
Summary: A command line application to easily create and run tornado applications.
Home-page: https://github.com/shubhodeep9/torn
Author: Shubhodeep Mukherjee
Author-email: shubhodeep9@gmail.com
License: Apache License, Version 2.0
Keywords: Tornado Web
Platform: UNKNOWN
Classifier: Development Status :: 3 - Alpha
Classifier: Programming Language :: Python
Classifier: Environment :: Console
Classifier: License :: OSI Approved :: Apache Software License
Classifier: Operating System :: OS Independent
Classifier: Programming Language :: Python :: 2
Classifier: Programming Language :: Python :: 2.4
Classifier: Programming Language :: Python :: 2.5
Classifier: Programming Language :: Python :: 2.6
Classifier: Programming Language :: Python :: 2.7
Classifier: Programming Language :: Python :: 3
Classifier: Programming Language :: Python :: 3.1
Classifier: Programming Language :: Python :: 3.2
Classifier: Programming Language :: Python :: 3.3
Classifier: Programming Language :: Python :: 3.4
Requires-Dist: tornado (>=4.3.0)
